tentoku/__init__.py
tentoku/_types.py
tentoku/benchmark.py
tentoku/build_database.py
tentoku/database_path.py
tentoku/deinflect.py
tentoku/deinflect_rules.py
tentoku/dictionary.py
tentoku/example_usage.py
tentoku/normalize.py
tentoku/sorting.py
tentoku/sqlite_dict.py
tentoku/tokenizer.py
tentoku/type_matching.py
tentoku/variations.py
tentoku/word_search.py
tentoku/yoon.py
tentoku-0.1.8.dist-info/licenses/LICENSE
tentoku-0.1.8.dist-info/METADATA
tentoku-0.1.8.dist-info/WHEEL
tentoku-0.1.8.dist-info/top_level.txt
tentoku-0.1.8.dist-info/RECORD
