Metadata-Version: 2.4
Name: tentoku
Version: 0.1.8
Summary: Japanese text tokenization with deinflection support, reimplementing the algorithm from 10ten Reader
Author: Tentoku Contributors
License-Expression: GPL-3.0-or-later
Classifier: Development Status :: 3 - Alpha
Classifier: Intended Audience :: Developers
Classifier: Programming Language :: Python :: 3
Classifier: Programming Language :: Python :: 3.8
Classifier: Programming Language :: Python :: 3.9
Classifier: Programming Language :: Python :: 3.10
Classifier: Programming Language :: Python :: 3.11
Classifier: Programming Language :: Python :: 3.12
Classifier: Programming Language :: Python :: 3.13
Classifier: Programming Language :: Python :: 3.14
Classifier: Topic :: Text Processing :: Linguistic
Requires-Python: >=3.8
License-File: LICENSE
Provides-Extra: dev
Requires-Dist: pytest>=7.0.0; extra == "dev"
Provides-Extra: full
Requires-Dist: lxml>=4.0.0; extra == "full"
Requires-Dist: tqdm>=4.0.0; extra == "full"
Dynamic: license-file
